orderedstructs.cpython-312-darwin.so
orderedstructs-0.4.0.dist-info/licenses/LICENSE
orderedstructs-0.4.0.dist-info/METADATA
orderedstructs-0.4.0.dist-info/WHEEL
orderedstructs-0.4.0.dist-info/top_level.txt
orderedstructs-0.4.0.dist-info/RECORD
