Metadata-Version: 2.4
Name: orderedstructs
Version: 0.4.0
Summary: Contains a variety of ordered structures, in particular a SkipList.
Home-page: https://github.com/paulross/skiplist
Download-URL: https://pypi.org/project/orderedstructs/
Author: Paul Ross
Author-email: apaulross@gmail.com
License: MIT License
Keywords: orderedstructs,SkipList
Classifier: Development Status :: 5 - Production/Stable
Classifier: Intended Audience :: Developers
Classifier: License :: OSI Approved :: MIT License
Classifier: Natural Language :: English
Classifier: Programming Language :: Python :: 3
Classifier: Programming Language :: Python :: 3.10
Classifier: Programming Language :: Python :: 3.11
Classifier: Programming Language :: Python :: 3.12
Classifier: Programming Language :: Python :: 3.13
Classifier: Programming Language :: Python :: 3.14
License-File: LICENSE
Dynamic: author
Dynamic: author-email
Dynamic: classifier
Dynamic: description
Dynamic: description-content-type
Dynamic: download-url
Dynamic: home-page
Dynamic: keywords
Dynamic: license
Dynamic: license-file
Dynamic: summary
